{"system":"阿里山林鐵時刻表","date":"20260721","source_notes":"時刻表來源:交通部 TDX v3/Rail/AFR/GeneralTrainTimetable(EffectiveDate=2024-02-15T00:00:00+08:00),2026-07 抓取,原始10車次、收錄50車次。 其中 42 班為官網補充:TDX 對沼平/神木兩支線只收每線最後一往返(53/54/120/121),完整班表(沼平12往返、神木11往返)依官方林鐵支線頁 afrch.forest.gov.tw/0000300 補齊,並與車站張貼紙本時刻表(2026-07 網友照片)逐班核對一致;TDX 已有班次以 TDX 為準。 靜態班表不收祝山線觀日列車(車次97,98):TDX 該兩班的 TrainInfo.Note 註明「停靠時間根據日出時間而定」,官方林鐵支線頁載明祝山線無固定時刻表、當日開車時間於乘車前1日16:30才公告(2026-07-19 官網公告04:20開車/回程末班06:10,TDX 常態表卻是08:00)。觀日列車改由前端依官方「祝山觀日平台日出時間概況表」逐日推算合成並標示「推算」(index.html addSunriseTrains;types 仍保留祝山線供其使用)。 TDX 未提供車種欄位(TrainInfo.TrainTypeID/TrainTypeName 十個車次全部為 null;v3/Rail/AFR/TrainType 雖列7種官方車種但未與班次資料建立關聯),故車種依「起訖站所屬路線」歸類:本線(嘉義↔十字路/阿里山)車次1,2,5,8→阿里山號;神木線車次120,121→神木線;沼平線車次53,54→沼平線(祝山線車次97,98 因上述日出因素排除,故 types 不含祝山線)。 加密方法同 scripts/densify_schedule.py 精神(節點=站名、邊=各線官方相鄰站、Dijkstra最短路徑插通過站、時刻依累積距離比例內插),差異:二萬平不在任何官方 StationOfLine 站序中,但時刻表確有車次(5,8)實際停靠,已依其在本線 shape 上的投影位置插入本線拓樸(於最近的前後官方站之間建邊)。 fallback區段(無法densify,保留原直線)=0/80。","types":[{"key":"阿里山號","color":"#B03A2E"},{"key":"神木線","color":"#CB6A4A"},{"key":"沼平線","color":"#D98A5F"},{"key":"祝山線","color":"#E0A458"}],"trains":[{"train":"1","typeName":"阿里山號","carName":"阿里山號","color":"#B03A2E","stops":[{"name":"嘉義","lat":23.479,"lon":120.4412,"order":1,"arrSec":32220,"depSec":32400,"stop":true},{"name":"北門","lat":23.488,"lon":120.4542,"order":2,"arrSec":32760,"depSec":33000,"stop":true},{"name":"鹿麻產","lat":23.5042,"lon":120.5315,"order":3,"arrSec":34320,"depSec":34380,"stop":true},{"name":"竹崎","lat":23.5258,"lon":120.5535,"order":4,"arrSec":34860,"depSec":34980,"stop":true},{"name":"樟腦寮","lat":23.5329,"lon":120.6025,"order":5,"arrSec":36540,"depSec":36600,"stop":true},{"name":"獨立山","lat":23.5385,"lon":120.6074,"order":6,"arrSec":37320,"depSec":37380,"stop":true},{"name":"梨園寮","lat":23.5423,"lon":120.62,"order":7,"arrSec":38100,"depSec":38160,"stop":true},{"name":"交力坪","lat":23.5314,"lon":120.6438,"order":8,"arrSec":38760,"depSec":38880,"stop":true},{"name":"水社寮","lat":23.5044,"lon":120.6596,"order":9,"arrSec":39840,"depSec":39900,"stop":true},{"name":"奮起湖","lat":23.5053,"lon":120.6951,"order":10,"arrSec":40860,"depSec":41400,"stop":true},{"name":"多林","lat":23.4987,"lon":120.7305,"order":11,"arrSec":42240,"depSec":42300,"stop":true},{"name":"十字路","lat":23.4928,"lon":120.7539,"order":12,"arrSec":43200,"depSec":43380,"stop":true}]},{"train":"120","typeName":"神木線","carName":"神木線","color":"#CB6A4A","stops":[{"name":"阿里山","lat":23.5099,"lon":120.8042,"order":1,"arrSec":56820,"depSec":57000,"stop":true},{"name":"神木","lat":23.5191,"lon":120.8064,"order":2,"arrSec":57420,"depSec":58200,"stop":true}]},{"train":"121","typeName":"神木線","carName":"神木線","color":"#CB6A4A","stops":[{"name":"神木","lat":23.5191,"lon":120.8064,"order":1,"arrSec":57420,"depSec":58200,"stop":true},{"name":"阿里山","lat":23.5099,"lon":120.8042,"order":2,"arrSec":58620,"depSec":58800,"stop":true}]},{"train":"2","typeName":"阿里山號","carName":"阿里山號","color":"#B03A2E","stops":[{"name":"十字路","lat":23.4928,"lon":120.7539,"order":1,"arrSec":47880,"depSec":48060,"stop":true},{"name":"多林","lat":23.4987,"lon":120.7305,"order":2,"arrSec":48900,"depSec":48960,"stop":true},{"name":"奮起湖","lat":23.5053,"lon":120.6951,"order":3,"arrSec":49800,"depSec":52260,"stop":true},{"name":"水社寮","lat":23.5044,"lon":120.6596,"order":4,"arrSec":53220,"depSec":53280,"stop":true},{"name":"交力坪","lat":23.5314,"lon":120.6438,"order":5,"arrSec":54300,"depSec":54360,"stop":true},{"name":"梨園寮","lat":23.5423,"lon":120.62,"order":6,"arrSec":55020,"depSec":55080,"stop":true},{"name":"獨立山","lat":23.5385,"lon":120.6074,"order":7,"arrSec":55800,"depSec":55860,"stop":true},{"name":"樟腦寮","lat":23.5329,"lon":120.6025,"order":8,"arrSec":56580,"depSec":56640,"stop":true},{"name":"竹崎","lat":23.5258,"lon":120.5535,"order":9,"arrSec":58260,"depSec":58320,"stop":true},{"name":"鹿麻產","lat":23.5042,"lon":120.5315,"order":10,"arrSec":58800,"depSec":58860,"stop":true},{"name":"北門","lat":23.488,"lon":120.4542,"order":11,"arrSec":60180,"depSec":60300,"stop":true},{"name":"嘉義","lat":23.479,"lon":120.4412,"order":12,"arrSec":60660,"depSec":60840,"stop":true}]},{"train":"5","typeName":"阿里山號","carName":"阿里山號","color":"#B03A2E","stops":[{"name":"嘉義","lat":23.479,"lon":120.4412,"order":1,"arrSec":35820,"depSec":36000,"stop":true},{"name":"北門","lat":23.488,"lon":120.4542,"order":2,"arrSec":36360,"depSec":36480,"stop":true},{"name":"鹿麻產","lat":23.5042,"lon":120.5315,"order":null,"arrSec":37760,"depSec":37760,"stop":false},{"name":"竹崎","lat":23.5258,"lon":120.5535,"order":3,"arrSec":38280,"depSec":38340,"stop":true},{"name":"樟腦寮","lat":23.5329,"lon":120.6025,"order":null,"arrSec":40237,"depSec":40237,"stop":false},{"name":"獨立山","lat":23.5385,"lon":120.6074,"order":null,"arrSec":40536,"depSec":40536,"stop":false},{"name":"梨園寮","lat":23.5423,"lon":120.62,"order":null,"arrSec":41043,"depSec":41043,"stop":false},{"name":"交力坪","lat":23.5314,"lon":120.6438,"order":4,"arrSec":42060,"depSec":42180,"stop":true},{"name":"水社寮","lat":23.5044,"lon":120.6596,"order":null,"arrSec":43140,"depSec":43140,"stop":false},{"name":"奮起湖","lat":23.5053,"lon":120.6951,"order":5,"arrSec":44160,"depSec":48060,"stop":true},{"name":"多林","lat":23.4987,"lon":120.7305,"order":null,"arrSec":49295,"depSec":49295,"stop":false},{"name":"十字路","lat":23.4928,"lon":120.7539,"order":null,"arrSec":50124,"depSec":50124,"stop":false},{"name":"屏遮那","lat":23.5106,"lon":120.7793,"order":null,"arrSec":51217,"depSec":51217,"stop":false},{"name":"第一分道","lat":23.5207,"lon":120.7943,"order":null,"arrSec":51853,"depSec":51853,"stop":false},{"name":"第二分道","lat":23.514,"lon":120.7909,"order":null,"arrSec":52128,"depSec":52128,"stop":false},{"name":"二萬平","lat":23.5089,"lon":120.7902,"order":6,"arrSec":52320,"depSec":52680,"stop":true},{"name":"神木","lat":23.5191,"lon":120.8064,"order":null,"arrSec":53389,"depSec":53389,"stop":false},{"name":"阿里山","lat":23.5099,"lon":120.8042,"order":7,"arrSec":53760,"depSec":53940,"stop":true}]},{"train":"53","typeName":"沼平線","carName":"沼平線","color":"#D98A5F","stops":[{"name":"阿里山","lat":23.5099,"lon":120.8042,"order":1,"arrSec":56160,"depSec":56400,"stop":true},{"name":"沼平","lat":23.5144,"lon":120.8138,"order":2,"arrSec":56760,"depSec":57000,"stop":true}]},{"train":"54","typeName":"沼平線","carName":"沼平線","color":"#D98A5F","stops":[{"name":"沼平","lat":23.5144,"lon":120.8138,"order":1,"arrSec":56760,"depSec":57600,"stop":true},{"name":"阿里山","lat":23.5099,"lon":120.8042,"order":2,"arrSec":57960,"depSec":58200,"stop":true}]},{"train":"8","typeName":"阿里山號","carName":"阿里山號","color":"#B03A2E","stops":[{"name":"阿里山","lat":23.5099,"lon":120.8042,"order":1,"arrSec":42420,"depSec":42600,"stop":true},{"name":"神木","lat":23.5191,"lon":120.8064,"order":null,"arrSec":42971,"depSec":42971,"stop":false},{"name":"二萬平","lat":23.5089,"lon":120.7902,"order":2,"arrSec":43680,"depSec":43740,"stop":true},{"name":"第二分道","lat":23.514,"lon":120.7909,"order":null,"arrSec":43929,"depSec":43929,"stop":false},{"name":"第一分道","lat":23.5207,"lon":120.7943,"order":null,"arrSec":44200,"depSec":44200,"stop":false},{"name":"屏遮那","lat":23.5106,"lon":120.7793,"order":null,"arrSec":44828,"depSec":44828,"stop":false},{"name":"十字路","lat":23.4928,"lon":120.7539,"order":null,"arrSec":45905,"depSec":45905,"stop":false},{"name":"多林","lat":23.4987,"lon":120.7305,"order":null,"arrSec":46723,"depSec":46723,"stop":false},{"name":"奮起湖","lat":23.5053,"lon":120.6951,"order":3,"arrSec":47940,"depSec":48540,"stop":true},{"name":"水社寮","lat":23.5044,"lon":120.6596,"order":null,"arrSec":49560,"depSec":49560,"stop":false},{"name":"交力坪","lat":23.5314,"lon":120.6438,"order":4,"arrSec":50520,"depSec":50640,"stop":true},{"name":"梨園寮","lat":23.5423,"lon":120.62,"order":null,"arrSec":51657,"depSec":51657,"stop":false},{"name":"獨立山","lat":23.5385,"lon":120.6074,"order":null,"arrSec":52164,"depSec":52164,"stop":false},{"name":"樟腦寮","lat":23.5329,"lon":120.6025,"order":null,"arrSec":52463,"depSec":52463,"stop":false},{"name":"竹崎","lat":23.5258,"lon":120.5535,"order":5,"arrSec":54360,"depSec":54420,"stop":true},{"name":"鹿麻產","lat":23.5042,"lon":120.5315,"order":null,"arrSec":54940,"depSec":54940,"stop":false},{"name":"北門","lat":23.488,"lon":120.4542,"order":6,"arrSec":56220,"depSec":56340,"stop":true},{"name":"嘉義","lat":23.479,"lon":120.4412,"order":7,"arrSec":56700,"depSec":56880,"stop":true}]},{"train":"31","typeName":"沼平線","carName":"沼平線","color":"#D98A5F","stops":[{"name":"阿里山","lat":23.5099,"lon":120.8042,"order":1,"arrSec":32220,"depSec":32400,"stop":true},{"name":"沼平","lat":23.5144,"lon":120.8138,"order":2,"arrSec":32760,"depSec":32940,"stop":true}]},{"train":"33","typeName":"沼平線","carName":"沼平線","color":"#D98A5F","stops":[{"name":"阿里山","lat":23.5099,"lon":120.8042,"order":1,"arrSec":34020,"depSec":34200,"stop":true},{"name":"沼平","lat":23.5144,"lon":120.8138,"order":2,"arrSec":34560,"depSec":34740,"stop":true}]},{"train":"35","typeName":"沼平線","carName":"沼平線","color":"#D98A5F","stops":[{"name":"阿里山","lat":23.5099,"lon":120.8042,"order":1,"arrSec":35820,"depSec":36000,"stop":true},{"name":"沼平","lat":23.5144,"lon":120.8138,"order":2,"arrSec":36360,"depSec":36540,"stop":true}]},{"train":"37","typeName":"沼平線","carName":"沼平線","color":"#D98A5F","stops":[{"name":"阿里山","lat":23.5099,"lon":120.8042,"order":1,"arrSec":37620,"depSec":37800,"stop":true},{"name":"沼平","lat":23.5144,"lon":120.8138,"order":2,"arrSec":38160,"depSec":38340,"stop":true}]},{"train":"39","typeName":"沼平線","carName":"沼平線","color":"#D98A5F","stops":[{"name":"阿里山","lat":23.5099,"lon":120.8042,"order":1,"arrSec":39420,"depSec":39600,"stop":true},{"name":"沼平","lat":23.5144,"lon":120.8138,"order":2,"arrSec":39960,"depSec":40140,"stop":true}]},{"train":"41","typeName":"沼平線","carName":"沼平線","color":"#D98A5F","stops":[{"name":"阿里山","lat":23.5099,"lon":120.8042,"order":1,"arrSec":41220,"depSec":41400,"stop":true},{"name":"沼平","lat":23.5144,"lon":120.8138,"order":2,"arrSec":41760,"depSec":41940,"stop":true}]},{"train":"43","typeName":"沼平線","carName":"沼平線","color":"#D98A5F","stops":[{"name":"阿里山","lat":23.5099,"lon":120.8042,"order":1,"arrSec":46620,"depSec":46800,"stop":true},{"name":"沼平","lat":23.5144,"lon":120.8138,"order":2,"arrSec":47160,"depSec":47340,"stop":true}]},{"train":"45","typeName":"沼平線","carName":"沼平線","color":"#D98A5F","stops":[{"name":"阿里山","lat":23.5099,"lon":120.8042,"order":1,"arrSec":48420,"depSec":48600,"stop":true},{"name":"沼平","lat":23.5144,"lon":120.8138,"order":2,"arrSec":48960,"depSec":49140,"stop":true}]},{"train":"47","typeName":"沼平線","carName":"沼平線","color":"#D98A5F","stops":[{"name":"阿里山","lat":23.5099,"lon":120.8042,"order":1,"arrSec":50220,"depSec":50400,"stop":true},{"name":"沼平","lat":23.5144,"lon":120.8138,"order":2,"arrSec":50760,"depSec":50940,"stop":true}]},{"train":"49","typeName":"沼平線","carName":"沼平線","color":"#D98A5F","stops":[{"name":"阿里山","lat":23.5099,"lon":120.8042,"order":1,"arrSec":52020,"depSec":52200,"stop":true},{"name":"沼平","lat":23.5144,"lon":120.8138,"order":2,"arrSec":52560,"depSec":52740,"stop":true}]},{"train":"51","typeName":"沼平線","carName":"沼平線","color":"#D98A5F","stops":[{"name":"阿里山","lat":23.5099,"lon":120.8042,"order":1,"arrSec":54420,"depSec":54600,"stop":true},{"name":"沼平","lat":23.5144,"lon":120.8138,"order":2,"arrSec":54960,"depSec":55140,"stop":true}]},{"train":"32","typeName":"沼平線","carName":"沼平線","color":"#D98A5F","stops":[{"name":"沼平","lat":23.5144,"lon":120.8138,"order":1,"arrSec":33420,"depSec":33600,"stop":true},{"name":"阿里山","lat":23.5099,"lon":120.8042,"order":2,"arrSec":33960,"depSec":34140,"stop":true}]},{"train":"34","typeName":"沼平線","carName":"沼平線","color":"#D98A5F","stops":[{"name":"沼平","lat":23.5144,"lon":120.8138,"order":1,"arrSec":35220,"depSec":35400,"stop":true},{"name":"阿里山","lat":23.5099,"lon":120.8042,"order":2,"arrSec":35760,"depSec":35940,"stop":true}]},{"train":"36","typeName":"沼平線","carName":"沼平線","color":"#D98A5F","stops":[{"name":"沼平","lat":23.5144,"lon":120.8138,"order":1,"arrSec":37020,"depSec":37200,"stop":true},{"name":"阿里山","lat":23.5099,"lon":120.8042,"order":2,"arrSec":37560,"depSec":37740,"stop":true}]},{"train":"38","typeName":"沼平線","carName":"沼平線","color":"#D98A5F","stops":[{"name":"沼平","lat":23.5144,"lon":120.8138,"order":1,"arrSec":38820,"depSec":39000,"stop":true},{"name":"阿里山","lat":23.5099,"lon":120.8042,"order":2,"arrSec":39360,"depSec":39540,"stop":true}]},{"train":"40","typeName":"沼平線","carName":"沼平線","color":"#D98A5F","stops":[{"name":"沼平","lat":23.5144,"lon":120.8138,"order":1,"arrSec":40620,"depSec":40800,"stop":true},{"name":"阿里山","lat":23.5099,"lon":120.8042,"order":2,"arrSec":41160,"depSec":41340,"stop":true}]},{"train":"42","typeName":"沼平線","carName":"沼平線","color":"#D98A5F","stops":[{"name":"沼平","lat":23.5144,"lon":120.8138,"order":1,"arrSec":42420,"depSec":42600,"stop":true},{"name":"阿里山","lat":23.5099,"lon":120.8042,"order":2,"arrSec":42960,"depSec":43140,"stop":true}]},{"train":"44","typeName":"沼平線","carName":"沼平線","color":"#D98A5F","stops":[{"name":"沼平","lat":23.5144,"lon":120.8138,"order":1,"arrSec":47820,"depSec":48000,"stop":true},{"name":"阿里山","lat":23.5099,"lon":120.8042,"order":2,"arrSec":48360,"depSec":48540,"stop":true}]},{"train":"46","typeName":"沼平線","carName":"沼平線","color":"#D98A5F","stops":[{"name":"沼平","lat":23.5144,"lon":120.8138,"order":1,"arrSec":49620,"depSec":49800,"stop":true},{"name":"阿里山","lat":23.5099,"lon":120.8042,"order":2,"arrSec":50160,"depSec":50340,"stop":true}]},{"train":"48","typeName":"沼平線","carName":"沼平線","color":"#D98A5F","stops":[{"name":"沼平","lat":23.5144,"lon":120.8138,"order":1,"arrSec":51420,"depSec":51600,"stop":true},{"name":"阿里山","lat":23.5099,"lon":120.8042,"order":2,"arrSec":51960,"depSec":52140,"stop":true}]},{"train":"50","typeName":"沼平線","carName":"沼平線","color":"#D98A5F","stops":[{"name":"沼平","lat":23.5144,"lon":120.8138,"order":1,"arrSec":53820,"depSec":54000,"stop":true},{"name":"阿里山","lat":23.5099,"lon":120.8042,"order":2,"arrSec":54360,"depSec":54540,"stop":true}]},{"train":"52","typeName":"沼平線","carName":"沼平線","color":"#D98A5F","stops":[{"name":"沼平","lat":23.5144,"lon":120.8138,"order":1,"arrSec":55620,"depSec":55800,"stop":true},{"name":"阿里山","lat":23.5099,"lon":120.8042,"order":2,"arrSec":56160,"depSec":56340,"stop":true}]},{"train":"100","typeName":"神木線","carName":"神木線","color":"#CB6A4A","stops":[{"name":"阿里山","lat":23.5099,"lon":120.8042,"order":1,"arrSec":34620,"depSec":34800,"stop":true},{"name":"神木","lat":23.5191,"lon":120.8064,"order":2,"arrSec":35220,"depSec":35400,"stop":true}]},{"train":"102","typeName":"神木線","carName":"神木線","color":"#CB6A4A","stops":[{"name":"阿里山","lat":23.5099,"lon":120.8042,"order":1,"arrSec":36420,"depSec":36600,"stop":true},{"name":"神木","lat":23.5191,"lon":120.8064,"order":2,"arrSec":37020,"depSec":37200,"stop":true}]},{"train":"104","typeName":"神木線","carName":"神木線","color":"#CB6A4A","stops":[{"name":"阿里山","lat":23.5099,"lon":120.8042,"order":1,"arrSec":38220,"depSec":38400,"stop":true},{"name":"神木","lat":23.5191,"lon":120.8064,"order":2,"arrSec":38820,"depSec":39000,"stop":true}]},{"train":"106","typeName":"神木線","carName":"神木線","color":"#CB6A4A","stops":[{"name":"阿里山","lat":23.5099,"lon":120.8042,"order":1,"arrSec":40020,"depSec":40200,"stop":true},{"name":"神木","lat":23.5191,"lon":120.8064,"order":2,"arrSec":40620,"depSec":40800,"stop":true}]},{"train":"108","typeName":"神木線","carName":"神木線","color":"#CB6A4A","stops":[{"name":"阿里山","lat":23.5099,"lon":120.8042,"order":1,"arrSec":41820,"depSec":42000,"stop":true},{"name":"神木","lat":23.5191,"lon":120.8064,"order":2,"arrSec":42420,"depSec":42600,"stop":true}]},{"train":"110","typeName":"神木線","carName":"神木線","color":"#CB6A4A","stops":[{"name":"阿里山","lat":23.5099,"lon":120.8042,"order":1,"arrSec":47220,"depSec":47400,"stop":true},{"name":"神木","lat":23.5191,"lon":120.8064,"order":2,"arrSec":47820,"depSec":48000,"stop":true}]},{"train":"112","typeName":"神木線","carName":"神木線","color":"#CB6A4A","stops":[{"name":"阿里山","lat":23.5099,"lon":120.8042,"order":1,"arrSec":49020,"depSec":49200,"stop":true},{"name":"神木","lat":23.5191,"lon":120.8064,"order":2,"arrSec":49620,"depSec":49800,"stop":true}]},{"train":"114","typeName":"神木線","carName":"神木線","color":"#CB6A4A","stops":[{"name":"阿里山","lat":23.5099,"lon":120.8042,"order":1,"arrSec":50820,"depSec":51000,"stop":true},{"name":"神木","lat":23.5191,"lon":120.8064,"order":2,"arrSec":51420,"depSec":51600,"stop":true}]},{"train":"116","typeName":"神木線","carName":"神木線","color":"#CB6A4A","stops":[{"name":"阿里山","lat":23.5099,"lon":120.8042,"order":1,"arrSec":52620,"depSec":52800,"stop":true},{"name":"神木","lat":23.5191,"lon":120.8064,"order":2,"arrSec":53220,"depSec":53400,"stop":true}]},{"train":"118","typeName":"神木線","carName":"神木線","color":"#CB6A4A","stops":[{"name":"阿里山","lat":23.5099,"lon":120.8042,"order":1,"arrSec":55020,"depSec":55200,"stop":true},{"name":"神木","lat":23.5191,"lon":120.8064,"order":2,"arrSec":55620,"depSec":55800,"stop":true}]},{"train":"101","typeName":"神木線","carName":"神木線","color":"#CB6A4A","stops":[{"name":"神木","lat":23.5191,"lon":120.8064,"order":1,"arrSec":35820,"depSec":36000,"stop":true},{"name":"阿里山","lat":23.5099,"lon":120.8042,"order":2,"arrSec":36420,"depSec":36600,"stop":true}]},{"train":"103","typeName":"神木線","carName":"神木線","color":"#CB6A4A","stops":[{"name":"神木","lat":23.5191,"lon":120.8064,"order":1,"arrSec":37620,"depSec":37800,"stop":true},{"name":"阿里山","lat":23.5099,"lon":120.8042,"order":2,"arrSec":38220,"depSec":38400,"stop":true}]},{"train":"105","typeName":"神木線","carName":"神木線","color":"#CB6A4A","stops":[{"name":"神木","lat":23.5191,"lon":120.8064,"order":1,"arrSec":39420,"depSec":39600,"stop":true},{"name":"阿里山","lat":23.5099,"lon":120.8042,"order":2,"arrSec":40020,"depSec":40200,"stop":true}]},{"train":"107","typeName":"神木線","carName":"神木線","color":"#CB6A4A","stops":[{"name":"神木","lat":23.5191,"lon":120.8064,"order":1,"arrSec":41220,"depSec":41400,"stop":true},{"name":"阿里山","lat":23.5099,"lon":120.8042,"order":2,"arrSec":41820,"depSec":42000,"stop":true}]},{"train":"109","typeName":"神木線","carName":"神木線","color":"#CB6A4A","stops":[{"name":"神木","lat":23.5191,"lon":120.8064,"order":1,"arrSec":43020,"depSec":43200,"stop":true},{"name":"阿里山","lat":23.5099,"lon":120.8042,"order":2,"arrSec":43620,"depSec":43800,"stop":true}]},{"train":"111","typeName":"神木線","carName":"神木線","color":"#CB6A4A","stops":[{"name":"神木","lat":23.5191,"lon":120.8064,"order":1,"arrSec":48420,"depSec":48600,"stop":true},{"name":"阿里山","lat":23.5099,"lon":120.8042,"order":2,"arrSec":49020,"depSec":49200,"stop":true}]},{"train":"113","typeName":"神木線","carName":"神木線","color":"#CB6A4A","stops":[{"name":"神木","lat":23.5191,"lon":120.8064,"order":1,"arrSec":50220,"depSec":50400,"stop":true},{"name":"阿里山","lat":23.5099,"lon":120.8042,"order":2,"arrSec":50820,"depSec":51000,"stop":true}]},{"train":"115","typeName":"神木線","carName":"神木線","color":"#CB6A4A","stops":[{"name":"神木","lat":23.5191,"lon":120.8064,"order":1,"arrSec":52020,"depSec":52200,"stop":true},{"name":"阿里山","lat":23.5099,"lon":120.8042,"order":2,"arrSec":52620,"depSec":52800,"stop":true}]},{"train":"117","typeName":"神木線","carName":"神木線","color":"#CB6A4A","stops":[{"name":"神木","lat":23.5191,"lon":120.8064,"order":1,"arrSec":54420,"depSec":54600,"stop":true},{"name":"阿里山","lat":23.5099,"lon":120.8042,"order":2,"arrSec":55020,"depSec":55200,"stop":true}]},{"train":"119","typeName":"神木線","carName":"神木線","color":"#CB6A4A","stops":[{"name":"神木","lat":23.5191,"lon":120.8064,"order":1,"arrSec":56220,"depSec":56400,"stop":true},{"name":"阿里山","lat":23.5099,"lon":120.8042,"order":2,"arrSec":56820,"depSec":57000,"stop":true}]}]}